Murray/__init__.py
Murray/auxiliary.py
Murray/main.py
Murray/plots.py
Murray/post_analysis.py
Murray/tests/__init__.py
Murray/tests/test_better_groups.py
Murray/tests/test_market_correlations.py
Murray/tests/test_power_analysis.py
Murray/tests/test_run_geo_analysis.py
Murray/tests/test_run_geo_evaluation.py
Murray/tests/test_select_markets.py
Murray/tests/test_synthetic_control.py
Murray/tests/test_upload_data.py
murray_geo-1.1.0.dist-info/licenses/LICENSE
murray_geo-1.1.0.dist-info/METADATA
murray_geo-1.1.0.dist-info/WHEEL
murray_geo-1.1.0.dist-info/top_level.txt
murray_geo-1.1.0.dist-info/RECORD
