Metadata-Version: 2.4
Name: murray-geo
Version: 1.1.0
Summary: A package for geographical incrementality testing
Home-page: https://github.com/entropyx/murray
Author: Entropy Team
Author-email: dev@entropy.tech
Project-URL: Entropy Homepage, https://entropy.tech/
Project-URL: Documentation, https://entropy.tech/murray/
Project-URL: Source Code, https://github.com/entropyx/murray
Keywords: incrementality testing,geography,experiment analysis,causal inference
Classifier: Development Status :: 5 - Production/Stable
Classifier: Intended Audience :: Developers
Classifier: Intended Audience :: Science/Research
Classifier: Topic :: Scientific/Engineering
Classifier: Programming Language :: Python :: 3.8
Classifier: Programming Language :: Python :: 3.9
Classifier: Programming Language :: Python :: 3.10
Classifier: License :: OSI Approved :: MIT License
Classifier: Operating System :: OS Independent
Requires-Python: >=3.8
License-File: LICENSE
Requires-Dist: pandas
Requires-Dist: numpy
Requires-Dist: scikit-learn
Requires-Dist: cvxpy
Requires-Dist: tqdm
Requires-Dist: matplotlib
Requires-Dist: seaborn
Requires-Dist: plotly
Requires-Dist: millify
Requires-Dist: statsmodels
Dynamic: author
Dynamic: author-email
Dynamic: classifier
Dynamic: description
Dynamic: description-content-type
Dynamic: home-page
Dynamic: keywords
Dynamic: license-file
Dynamic: project-url
Dynamic: requires-dist
Dynamic: requires-python
Dynamic: summary
